ksfeatureselector/__init__.py
ksfeatureselector/core.py
tests/test_core.py
ksfeatureselector-0.2.0.dist-info/METADATA
ksfeatureselector-0.2.0.dist-info/WHEEL
ksfeatureselector-0.2.0.dist-info/top_level.txt
ksfeatureselector-0.2.0.dist-info/RECORD
