Metadata-Version: 2.4
Name: ksfeatureselector
Version: 0.2.0
Summary: A robust and flexible Python package designed for selecting the most discriminatory features in both **binary and multi-class classification problems** using the Kolmogorov-Smirnov (K-S) test. It provides advanced options for handling multi-class scenarios and aggregating p-values.
Author: V Subrahmanya Raghu Ram Kishore Parupudi
Author-email: V Subrahmanya Raghu Ram Kishore Parupudi <pvsrrkishore@gmail.com>
License: MIT
Requires-Python: >=3.7
Requires-Dist: pandas>=1.0.0
Requires-Dist: scipy>=1.5.0
Dynamic: author
Dynamic: requires-python
